MANIFEST.in
README.md
requirements.txt
setup.py
goto_project/__init__.py
goto_project/config_tools.py
goto_project/exceptions.py
goto_project/goto.py
goto_project/gt
goto_project/manager.py
goto_project/shell_tools.py
goto_project.egg-info/PKG-INFO
goto_project.egg-info/SOURCES.txt
goto_project.egg-info/dependency_links.txt
goto_project.egg-info/requires.txt
goto_project.egg-info/top_level.txt