Metadata-Version: 1.2
Name: goto-project
Version: 0.1.1
Summary: Easy and fast project switching in your shell!
Home-page: https://github.com/sivakov512/goto-project
Author: Nikita Sivakov
Author-email: sivakov.512@gmail.com
License: MIT
Keywords: project shell management
Platform: UNKNOWN
Requires-Python: >=3.6
